hallu/__init__.py
hallu/__version__.py
hallu/hallu.py
hallu-0.0.1.dist-info/LICENSE
hallu-0.0.1.dist-info/METADATA
hallu-0.0.1.dist-info/WHEEL
hallu-0.0.1.dist-info/entry_points.txt
hallu-0.0.1.dist-info/top_level.txt
hallu-0.0.1.dist-info/RECORD
